{
  "Header": {
    "WolvenKitVersion": "8.14.1-nightly.2024-09-17",
    "WKitJsonVersion": "0.0.9",
    "GameVersion": 2120,
    "ExportedDateTime": "2024-09-20T19:06:33.1099042Z",
    "DataType": "CR2W",
    "ArchiveFileName": "D:\\DocWorks Automotive (MODS)\\Wkit Project Files\\DWA-Arcadia-Mark-V\\source\\archive\\base\\vehicles\\docworks\\dwa_arcadia_collision.phys"
  },
  "Data": {
    "Version": 195,
    "BuildVersion": 0,
    "RootChunk": {
      "$type": "physicsSystemResource",
      "bodies": [
        {
          "HandleId": "0",
          "Data": {
            "$type": "physicsSystemBody",
            "collisionShapes": [
              {
                "HandleId": "1",
                "Data": {
                  "$type": "physicsColliderConvex",
                  "compiledGeometryBuffer": null,
                  "filterData": null,
                  "indexBuffer": [],
                  "isImported": 0,
                  "isQueryShapeOnly": 0,
                  "localToBody": {
                    "$type": "Transform",
                    "orientation": {
                      "$type": "Quaternion",
                      "i": 0,
                      "j": 0,
                      "k": 0,
                      "r": 1
                    },
                    "position": {
                      "$type": "Vector4",
                      "W": 0,
                      "X": 0,
                      "Y": 0,
                      "Z": 0
                    }
                  },
                  "material": {
                    "$type": "CName",
                    "$storage": "string",
                    "$value": "None"
                  },
                  "materialApperanceOverrides": [],
                  "polygonVertices": [],
                  "tag": {
                    "$type": "CName",
                    "$storage": "string",
                    "$value": "body"
                  },
                  "vertices": [
                    {
                      "$type": "Vector3",
                      "X": -1.01352525,
                      "Y": 2.51018262,
                      "Z": -0.203208461
                    },
                    {
                      "$type": "Vector3",
                      "X": -1.15220582,
                      "Y": -1.165187,
                      "Z": -0.189961776
                    },
                    {
                      "$type": "Vector3",
                      "X": 1.01352525,
                      "Y": 2.51018262,
                      "Z": -0.203208461
                    },
                    {
                      "$type": "Vector3",
                      "X": -1.07161868,
                      "Y": 1.98292363,
                      "Z": 0.0663192868
                    },
                    {
                      "$type": "Vector3",
                      "X": -1.3130095,
                      "Y": -1.78943598,
                      "Z": 0.0416015498
                    },
                    {
                      "$type": "Vector3",
                      "X": 1.15220582,
                      "Y": -1.165187,
                      "Z": -0.189961776
                    },
                    {
                      "$type": "Vector3",
                      "X": 1.07161868,
                      "Y": 1.98292363,
                      "Z": 0.0663192868
                    },
                    {
                      "$type": "Vector3",
                      "X": -0.916750014,
                      "Y": -2.98195839,
                      "Z": 0.0293132942
                    },
                    {
                      "$type": "Vector3",
                      "X": -0.364946842,
                      "Y": -2.97527766,
                      "Z": 0.359521657
                    },
                    {
                      "$type": "Vector3",
                      "X": -1.03520072,
                      "Y": -2.67692423,
                      "Z": -0.0569391251
                    },
                    {
                      "$type": "Vector3",
                      "X": 1.3130095,
                      "Y": -1.78943598,
                      "Z": 0.0416015498
                    },
                    {
                      "$type": "Vector3",
                      "X": -1.1659168,
                      "Y": -2.23440027,
                      "Z": -0.245867401
                    },
                    {
                      "$type": "Vector3",
                      "X": -0.959555387,
                      "Y": 0.700110316,
                      "Z": 0.331503808
                    },
                    {
                      "$type": "Vector3",
                      "X": -0.832743704,
                      "Y": -1.01559055,
                      "Z": 0.486233592
                    },
                    {
                      "$type": "Vector3",
                      "X": 0.916750014,
                      "Y": -2.98195839,
                      "Z": 0.0293132942
                    },
                    {
                      "$type": "Vector3",
                      "X": 0.364946842,
                      "Y": -2.97527766,
                      "Z": 0.359521657
                    },
                    {
                      "$type": "Vector3",
                      "X": 1.03520072,
                      "Y": -2.67692423,
                      "Z": -0.0569391251
                    },
                    {
                      "$type": "Vector3",
                      "X": 1.1659168,
                      "Y": -2.23440027,
                      "Z": -0.245867401
                    },
                    {
                      "$type": "Vector3",
                      "X": 0.959555387,
                      "Y": 0.700110316,
                      "Z": 0.331503808
                    },
                    {
                      "$type": "Vector3",
                      "X": 0.832743704,
                      "Y": -1.01559055,
                      "Z": 0.486233592
                    },
                    {
                      "$type": "Vector3",
                      "X": -0.640640855,
                      "Y": 2.54817605,
                      "Z": -0.24573943
                    },
                    {
                      "$type": "Vector3",
                      "X": 0,
                      "Y": 2.74717116,
                      "Z": -0.158061579
                    },
                    {
                      "$type": "Vector3",
                      "X": 0.640640855,
                      "Y": 2.54817605,
                      "Z": -0.24573943
                    },
                    {
                      "$type": "Vector3",
                      "X": 0.000135002309,
                      "Y": 2.74823093,
                      "Z": -0.183922276
                    },
                    {
                      "$type": "Vector3",
                      "X": -0.986394405,
                      "Y": -2.92830682,
                      "Z": 0.242745623
                    },
                    {
                      "$type": "Vector3",
                      "X": -0.876117468,
                      "Y": 2.61313844,
                      "Z": -0.177161276
                    },
                    {
                      "$type": "Vector3",
                      "X": 0.986394405,
                      "Y": -2.92830682,
                      "Z": 0.242745623
                    },
                    {
                      "$type": "Vector3",
                      "X": -0.834272742,
                      "Y": 0.583220243,
                      "Z": -0.264605165
                    },
                    {
                      "$type": "Vector3",
                      "X": 0.876117468,
                      "Y": 2.61313844,
                      "Z": -0.177161276
                    },
                    {
                      "$type": "Vector3",
                      "X": -1.05825925,
                      "Y": 2.09297872,
                      "Z": -0.255129904
                    },
                    {
                      "$type": "Vector3",
                      "X": 0.834272742,
                      "Y": 0.583220243,
                      "Z": -0.264605165
                    },
                    {
                      "$type": "Vector3",
                      "X": 0,
                      "Y": -3.01315188,
                      "Z": 0.0767441988
                    },
                    {
                      "$type": "Vector3",
                      "X": 0,
                      "Y": -2.97527766,
                      "Z": 0.359521657
                    },
                    {
                      "$type": "Vector3",
                      "X": 0,
                      "Y": -0.865553319,
                      "Z": 0.513379037
                    },
                    {
                      "$type": "Vector3",
                      "X": 0,
                      "Y": -2.17755222,
                      "Z": -0.301995069
                    },
                    {
                      "$type": "Vector3",
                      "X": 0,
                      "Y": -2.80094028,
                      "Z": 0.00980073214
                    },
                    {
                      "$type": "Vector3",
                      "X": 0,
                      "Y": 2.55733204,
                      "Z": -0.256749541
                    },
                    {
                      "$type": "Vector3",
                      "X": 0,
                      "Y": 0.425670713,
                      "Z": -0.294817746
                    },
                    {
                      "$type": "Vector3",
                      "X": 0,
                      "Y": 2.07315183,
                      "Z": 0.109152153
                    },
                    {
                      "$type": "Vector3",
                      "X": 0,
                      "Y": 2.74770093,
                      "Z": -0.188556746
                    },
                    {
                      "$type": "Vector3",
                      "X": 0,
                      "Y": 2.74539948,
                      "Z": -0.152104154
                    },
                    {
                      "$type": "Vector3",
                      "X": 0,
                      "Y": 2.74717116,
                      "Z": -0.158061579
                    },
                    {
                      "$type": "Vector3",
                      "X": -0.000135934621,
                      "Y": 2.7482307,
                      "Z": -0.183922932
                    },
                    {
                      "$type": "Vector3",
                      "X": 0,
                      "Y": 2.74717283,
                      "Z": -0.158095971
                    },
                    {
                      "$type": "Vector3",
                      "X": -0.376922756,
                      "Y": 2.74714136,
                      "Z": -0.161963522
                    },
                    {
                      "$type": "Vector3",
                      "X": 1.05825925,
                      "Y": 2.09297872,
                      "Z": -0.255129904
                    },
                    {
                      "$type": "Vector3",
                      "X": -0.966782093,
                      "Y": -1.81693017,
                      "Z": 0.292041659
                    },
                    {
                      "$type": "Vector3",
                      "X": -0.948859394,
                      "Y": 0.608351707,
                      "Z": 0.296954274
                    },
                    {
                      "$type": "Vector3",
                      "X": -0.473251015,
                      "Y": -0.352146387,
                      "Z": 0.641582489
                    },
                    {
                      "$type": "Vector3",
                      "X": 0,
                      "Y": -0.225781217,
                      "Z": 0.639815688
                    },
                    {
                      "$type": "Vector3",
                      "X": 0,
                      "Y": -1.96641254,
                      "Z": 0.372637719
                    },
                    {
                      "$type": "Vector3",
                      "X": 0,
                      "Y": 0.593328595,
                      "Z": 0.293441266
                    },
                    {
                      "$type": "Vector3",
                      "X": -0.959843636,
                      "Y": -2.82242656,
                      "Z": 0.276361227
                    },
                    {
                      "$type": "Vector3",
                      "X": -0.899101675,
                      "Y": -3.0250926,
                      "Z": 0.390825093
                    },
                    {
                      "$type": "Vector3",
                      "X": 0,
                      "Y": -3.02134252,
                      "Z": 0.393605471
                    },
                    {
                      "$type": "Vector3",
                      "X": 0,
                      "Y": -2.6020143,
                      "Z": 0.280564964
                    },
                    {
                      "$type": "Vector3",
                      "X": 0,
                      "Y": -2.92004442,
                      "Z": 0.244941384
                    },
                    {
                      "$type": "Vector3",
                      "X": 0,
                      "Y": 2.74706984,
                      "Z": -0.161258221
                    },
                    {
                      "$type": "Vector3",
                      "X": 0.376922756,
                      "Y": 2.74714136,
                      "Z": -0.161963522
                    },
                    {
                      "$type": "Vector3",
                      "X": 0.966782093,
                      "Y": -1.81693017,
                      "Z": 0.292041659
                    },
                    {
                      "$type": "Vector3",
                      "X": 0.948859394,
                      "Y": 0.608351707,
                      "Z": 0.296954274
                    },
                    {
                      "$type": "Vector3",
                      "X": 0.473251015,
                      "Y": -0.352146387,
                      "Z": 0.641582489
                    },
                    {
                      "$type": "Vector3",
                      "X": 0.959843636,
                      "Y": -2.82242656,
                      "Z": 0.276361227
                    },
                    {
                      "$type": "Vector3",
                      "X": 0.899101675,
                      "Y": -3.0250926,
                      "Z": 0.390825093
                    }
                  ],
                  "volumeModifier": 1
                }
              }
            ],
            "isQueryBodyOnly": 0,
            "localToModel": {
              "$type": "Transform",
              "orientation": {
                "$type": "Quaternion",
                "i": 0,
                "j": 0,
                "k": 0,
                "r": 1
              },
              "position": {
                "$type": "Vector4",
                "W": 0,
                "X": 0,
                "Y": 0,
                "Z": 0
              }
            },
            "mappedBoneName": {
              "$type": "CName",
              "$storage": "string",
              "$value": "None"
            },
            "mappedBoneToBody": {
              "$type": "Transform",
              "orientation": {
                "$type": "Quaternion",
                "i": 0,
                "j": 0,
                "k": 0,
                "r": 1
              },
              "position": {
                "$type": "Vector4",
                "W": 0,
                "X": 0,
                "Y": 0,
                "Z": 0
              }
            },
            "name": {
              "$type": "CName",
              "$storage": "string",
              "$value": "Actor (ID: 3, Mass: 1.633e\u002B04, bone: None )"
            },
            "params": {
              "$type": "physicsSystemBodyParams",
              "angularDamping": 0,
              "comOffset": {
                "$type": "Transform",
                "orientation": {
                  "$type": "Quaternion",
                  "i": -0.014652417,
                  "j": -0.000934042735,
                  "k": 0.00159091863,
                  "r": 0.999891043
                },
                "position": {
                  "$type": "Vector4",
                  "W": 0,
                  "X": -0.00439805305,
                  "Y": -0.20568262,
                  "Z": -0.149401605
                }
              },
              "inertia": {
                "$type": "Vector3",
                "X": 32071.9199,
                "Y": 6841.29639,
                "Z": 36104.4414
              },
              "linearDamping": 0,
              "mass": 16327.1025,
              "maxAngularVelocity": -1,
              "maxContactImpulse": -1,
              "maxDepenetrationVelocity": -1,
              "simulationType": "Static",
              "solverIterationsCountPosition": 4,
              "solverIterationsCountVelocity": 1
            }
          }
        }
      ],
      "cookingPlatform": "PLATFORM_PC",
      "joints": []
    },
    "EmbeddedFiles": []
  }
}